llm_url_markdown.py
llm_url_markdown-0.1.dist-info/METADATA
llm_url_markdown-0.1.dist-info/WHEEL
llm_url_markdown-0.1.dist-info/entry_points.txt
llm_url_markdown-0.1.dist-info/top_level.txt
llm_url_markdown-0.1.dist-info/RECORD
