Metadata-Version: 2.4
Name: llm-url-markdown
Version: 0.1
Summary: Plugin for LLM that adds support for fetching markdown content from URLs using Jina Reader API
Author: Saeed Esmaili
License: Apache-2.0
Requires-Python: >=3.9
Requires-Dist: llm>=0.24
